{
  "buckets": [
    {
      "name": "dssfds",
      "id": 1
    },
    {
      "name": "fdsgfdgd",
      "id": 2
    }
  ],
  "cards": [
    {
      "card": "asdasd",
      "name": "dsadsa",
      "id": 1
    },
    {
      "card": "asdasd",
      "name": "dasda",
      "id": 2
    },
    {
      "bucketName": "dssfds",
      "card": "https://www.youtube.com/watch?v=GXBlqJCnEXE",
      "name": "car",
      "id": 3
    },
    {
      "bucketName": "dssfds",
      "card": "https://www.youtube.com/watch?v=GXBlqJCnEXE",
      "name": "dsad",
      "id": 4
    },
    {
      "bucketName": "dssfds",
      "card": "fsafas",
      "name": "fafdad",
      "id": 5
    },
    {
      "bucketName": "dssfds",
      "card": "dasfad",
      "name": "dasdasd",
      "id": 6
    },
    {
      "bucketName": "fdsgfdgd",
      "card": "https://www.youtube.com/watch?v=GXBlqJCnEXE",
      "name": "dsfsdfa",
      "id": 7
    },
    {
      "bucketName": "fdsgfdgd",
      "card": "https://www.youtube.com/watch?v=GXBlqJCnEXE",
      "name": "dsadasdasd",
      "id": 8
    },
    {
      "bucketName": "fdsgfdgd",
      "card": "https://www.youtube.com/watch?v=GXBlqJCnEXE",
      "name": "sfasfdfaf",
      "id": 9
    },
    {
      "bucketName": "dssfds",
      "card": "asdasdad",
      "name": "dasdasd",
      "id": 10
    }
  ],
  "history": []
}